tapk.py
TAP_k-1.0.dist-info/LICENSE.md
TAP_k-1.0.dist-info/METADATA
TAP_k-1.0.dist-info/WHEEL
TAP_k-1.0.dist-info/entry_points.txt
TAP_k-1.0.dist-info/top_level.txt
TAP_k-1.0.dist-info/RECORD
