Metadata-Version: 2.1
Name: TAP-k
Version: 1.0
Summary: Threshold Average Precision: metric for evaluating retrieval rankings
Home-page: https://github.com/OntoGene/TAP-k
Author: Lenz Furrer
Author-email: furrer@cl.uzh.ch
License: UNKNOWN
Platform: UNKNOWN
Classifier: Programming Language :: Python :: 3
Classifier: License :: OSI Approved :: BSD License
Classifier: Operating System :: OS Independent
Requires-Python: >=3
